{"message": "\u641c\u7d22\u6210\u529f", "result": {"user": {"max_score": null, "total": 0, "hits": []}, "success": 0, "post": {"max_score": 2.0649285, "total": 1, "hits": [{"_score": 2.0649285, "_id": "1", "_index": "cnddu", "_source": {"postid": 1, "name": "react-enlightenment", "cover": "3a4672d8-90c4-11e7-8712-00163e0f3b4a.png", "description": "React Enlightenment", "title": "React Enlightenment"}, "_type": "post"},{"_score": 2.0649285, "_id": "1", "_index": "cnddu", "_source": {"postid": 1, "name": "react-enlightenment", "cover": "3a4672d8-90c4-11e7-8712-00163e0f3b4a.png", "description": "React Enlightenment", "title": "React Enlightenment"}, "_type": "post"}]}}, "code": 0}
